{"consentFlowEnabled":true,"consentFlowPrivacyPolicyUrl":"https://lionstudios.cc/privacy/","consentFlowTermsOfServiceUrl":"https://lionstudios.cc/terms/","overrideDefaultUserTrackingUsageDescriptions":false,"debugUserGeography":0,"userTrackingUsageDescriptionEn":"","userTrackingUsageLocalizationEnabled":true,"userTrackingUsageDescriptionDe":"","userTrackingUsageDescriptionEs":"","userTrackingUsageDescriptionFr":"","userTrackingUsageDescriptionJa":"","userTrackingUsageDescriptionKo":"","userTrackingUsageDescriptionZhHans":"","userTrackingUsageDescriptionZhHant":""}